tests/__init__.py
tests/conftest.py
tests/test_validation_urkund.py
tests/utils.py
urkund/__init__.py
urkund/data/VERSION
urkund/provider/__init__.py
urkund/provider/urkund.py
urkund/provider/utils.py
urkund/urkund_lib/__init__.py
urkund/urkund_lib/receivers.py
urkund/urkund_lib/request.py
urkund/urkund_lib/submissions.py
urkund/urkund_lib/units.py
urkund/urkund_lib/exceptions/__init__.py
urkund/urkund_lib/exceptions/bad_request.py
urkund/urkund_lib/exceptions/base_urkund_lib_exception.py
urkund/urkund_lib/exceptions/invalid_response.py
urkund/urkund_lib/exceptions/media_type_not_supported.py
urkund/urkund_lib/exceptions/mime_type_not_supported.py
urkund/urkund_lib/exceptions/not_available.py
urkund/urkund_lib/exceptions/not_found.py
urkund/urkund_lib/exceptions/receiver_exists.py
urkund/urkund_lib/exceptions/request_too_large.py
urkund/urkund_lib/exceptions/submission_not_found.py
urkund/urkund_lib/exceptions/timeout.py
urkund/urkund_lib/exceptions/unauthorized.py
urkund/urkund_lib/exceptions/unit_and_organization_not_valid.py
tesla_ce_provider_pt_urkund-0.0.6.dist-info/LICENSE
tesla_ce_provider_pt_urkund-0.0.6.dist-info/METADATA
tesla_ce_provider_pt_urkund-0.0.6.dist-info/WHEEL
tesla_ce_provider_pt_urkund-0.0.6.dist-info/top_level.txt
tesla_ce_provider_pt_urkund-0.0.6.dist-info/RECORD
