Metadata-Version: 2.1
Name: tesla-ce-provider-pt-urkund
Version: 0.0.6
Summary: TeSLA CE Urkund Plagiarism Provider
Home-page: https://tesla-ce.github.io
Author: Roger Muñoz Bernaus
Author-email: rmunozber@uoc.edu
License: UNKNOWN
Project-URL: Documentation, https://tesla-ce.github.io/provider-pt-urkund/
Project-URL: Source, https://github.com/tesla-ce/provider-pt-urkund
Platform: UNKNOWN
Classifier: Programming Language :: Python :: 3
Classifier: License :: OSI Approved :: GNU Affero General Public License v3 or later (AGPLv3+)
Classifier: Operating System :: POSIX :: Linux
Requires-Python: >=3.8
License-File: LICENSE
Requires-Dist: amqp (==5.1.1)
Requires-Dist: backports.zoneinfo[tzdata] (==0.2.1)
Requires-Dist: billiard (==4.1.0)
Requires-Dist: celery (==5.3.1)
Requires-Dist: certifi (==2023.7.22)
Requires-Dist: charset-normalizer (==3.2.0)
Requires-Dist: click-didyoumean (==0.3.0)
Requires-Dist: click-plugins (==1.1.1)
Requires-Dist: click-repl (==0.3.0)
Requires-Dist: click (==8.1.6)
Requires-Dist: deprecation (==2.1.0)
Requires-Dist: gevent (==23.7.0)
Requires-Dist: greenlet (==2.0.2)
Requires-Dist: idna (==3.4)
Requires-Dist: kombu (==5.3.1)
Requires-Dist: packaging (==23.1)
Requires-Dist: prompt-toolkit (==3.0.39)
Requires-Dist: python-dateutil (==2.8.2)
Requires-Dist: python-magic (==0.4.27)
Requires-Dist: requests (==2.31.0)
Requires-Dist: sentry-sdk (==1.28.1)
Requires-Dist: simplejson (==3.19.1)
Requires-Dist: six (==1.16.0)
Requires-Dist: tesla-ce-client (==0.0.4)
Requires-Dist: tesla-ce-provider (==0.0.9)
Requires-Dist: typing-extensions (==4.7.1)
Requires-Dist: tzdata (==2023.3)
Requires-Dist: urllib3 (==2.0.4)
Requires-Dist: vine (==5.0.0)
Requires-Dist: wcwidth (==0.2.6)
Requires-Dist: zope.event (==5.0)
Requires-Dist: zope.interface (==6.0)
